simple_sphinx_xml_sitemap/__init__.py
simple_sphinx_xml_sitemap/sitemap.py
simple_sphinx_xml_sitemap-0.1.2.dist-info/licenses/LICENSE
simple_sphinx_xml_sitemap-0.1.2.dist-info/METADATA
simple_sphinx_xml_sitemap-0.1.2.dist-info/WHEEL
simple_sphinx_xml_sitemap-0.1.2.dist-info/top_level.txt
simple_sphinx_xml_sitemap-0.1.2.dist-info/RECORD
