Metadata-Version: 2.4
Name: simple-sphinx-xml-sitemap
Version: 0.1.2
Summary: A simple Sphinx extension that generates an XML sitemap from navigation pages.
Author: Matthew Rideout
License: MIT License
Project-URL: Homepage, https://github.com/mdrideout/simple-sphinx-xml-sitemap
Requires-Python: >=3.8
License-File: LICENSE
Requires-Dist: Sphinx>=4
Provides-Extra: dev
Requires-Dist: pytest>=7; extra == "dev"
Dynamic: license-file
